{"name":"adicionar relacionamento entre tarefas","id":"criar-nova-tarefa;adicionar-relacionamento-entre-tarefas","testSteps":[{"number":1,"description":"Abrir Mantis","duration":722,"startTime":"2020-12-09T17:28:52.949-03:00[America/Sao_Paulo]","screenshots":[{"screenshot":"20751074aa616d8ca32771653149891b111e8474db230b8c59b587eca783e230.png","timeStamp":1607545733671}],"result":"SUCCESS","precondition":false,"level":0},{"number":2,"description":"Preencher usuário com \u0027administrator\u0027","duration":436,"startTime":"2020-12-09T17:28:53.672-03:00[America/Sao_Paulo]","screenshots":[{"screenshot":"f253a7bf9b1dbe68897d229ece9f30eed6040e767175ee6ad7d5b4a098b02cef.png","timeStamp":1607545734108}],"result":"SUCCESS","precondition":false,"level":0},{"number":3,"description":"Clicar em \u0027Login\u0027","duration":605,"startTime":"2020-12-09T17:28:54.109-03:00[America/Sao_Paulo]","screenshots":[{"screenshot":"3a2498f18daea4991195fc522036a7a7fcf99153bb5493a9ebb867ee499a26ca.png","timeStamp":1607545734714}],"result":"SUCCESS","precondition":false,"level":0},{"number":4,"description":"Preencher senha com \u0027[0}\u0027","duration":419,"startTime":"2020-12-09T17:28:54.715-03:00[America/Sao_Paulo]","screenshots":[{"screenshot":"6653342e027a26d83a6bdb40034c4a3699f9e894bcd1ef855f4cbc5175ef1fb6.png","timeStamp":1607545735134}],"result":"SUCCESS","precondition":false,"level":0},{"number":5,"description":"Clicar em \u0027Login\u0027","duration":1041,"startTime":"2020-12-09T17:28:55.134-03:00[America/Sao_Paulo]","screenshots":[{"screenshot":"680b498deed0b2550badb97a8f36d96009e1001e7e466ce2dc30a749a0187034.png","timeStamp":1607545736175}],"result":"SUCCESS","precondition":false,"level":0},{"number":6,"description":"Given que estou logado como administrador no sistema","duration":500,"startTime":"2020-12-09T17:28:56.175-03:00[America/Sao_Paulo]","screenshots":[{"screenshot":"680b498deed0b2550badb97a8f36d96009e1001e7e466ce2dc30a749a0187034.png","timeStamp":1607545736675}],"result":"SUCCESS","precondition":false,"level":0,"children":[{"number":7,"description":"Retorna username das informações de login","duration":434,"startTime":"2020-12-09T17:28:56.240-03:00[America/Sao_Paulo]","screenshots":[{"screenshot":"680b498deed0b2550badb97a8f36d96009e1001e7e466ce2dc30a749a0187034.png","timeStamp":1607545736674}],"result":"SUCCESS","precondition":false,"level":1}]},{"number":8,"description":"When clico em \u0027Criar Tarefa\u0027","duration":663,"startTime":"2020-12-09T17:28:56.675-03:00[America/Sao_Paulo]","screenshots":[{"screenshot":"14e1a394d25584a1ac677753814ab535c6b2caceec19f6668939310f71e807b6.png","timeStamp":1607545737338}],"result":"SUCCESS","precondition":false,"level":0,"children":[{"number":9,"description":"main: Clicar Em Criar Tarefa","duration":583,"startTime":"2020-12-09T17:28:56.754-03:00[America/Sao_Paulo]","screenshots":[{"screenshot":"14e1a394d25584a1ac677753814ab535c6b2caceec19f6668939310f71e807b6.png","timeStamp":1607545737337}],"result":"SUCCESS","precondition":false,"level":1}]},{"number":10,"description":"And preencho os detalhes do relatorio\r\n| Categoria | Frequencia | Gravidade | Prioridade | Selecionar Perfil | Plataforma | SO | Versao SO | Atribuir | Resumo | Descricao | Passos Reproduzir | informacoes Adicionais | Aplicar Marcadores | Anexo | Visibilidade |\r\n| categ inicial | sempre | pequeno | normal | Sim | plat teste | win | 10 | administrator | Tarefa de teste para apagar | Descricao de tarefa de teste automatizado | clicar e preencher | outro teste | . | Nao | publico |","duration":6977,"startTime":"2020-12-09T17:28:57.338-03:00[America/Sao_Paulo]","screenshots":[{"screenshot":"be5ba05b7a0318324485c3bb94bb442bc5ffab57436aee18cd07a95675905a87.png","timeStamp":1607545744315}],"result":"SUCCESS","precondition":false,"level":0,"children":[{"number":11,"description":"Criar Tarefa: Selecionar Categoria","duration":474,"startTime":"2020-12-09T17:28:57.339-03:00[America/Sao_Paulo]","screenshots":[{"screenshot":"46b18801200c340fb26709303ad3a50fcde25587ce98ebf312569319bd2e4f90.png","timeStamp":1607545737813}],"result":"SUCCESS","precondition":false,"level":1},{"number":12,"description":"Criar Tarefa: Selecionar Frequencia","duration":474,"startTime":"2020-12-09T17:28:57.813-03:00[America/Sao_Paulo]","screenshots":[{"screenshot":"6e04e284f9f999280e0824cddce73db3c30af8cd9a3558d48def341eb05bb5b2.png","timeStamp":1607545738287}],"result":"SUCCESS","precondition":false,"level":1},{"number":13,"description":"Criar Tarefa: Selecionar Gravidade","duration":414,"startTime":"2020-12-09T17:28:58.288-03:00[America/Sao_Paulo]","screenshots":[{"screenshot":"6e04e284f9f999280e0824cddce73db3c30af8cd9a3558d48def341eb05bb5b2.png","timeStamp":1607545738702}],"result":"SUCCESS","precondition":false,"level":1},{"number":14,"description":"Criar Tarefa: Selecionar Prioridade","duration":450,"startTime":"2020-12-09T17:28:58.703-03:00[America/Sao_Paulo]","screenshots":[{"screenshot":"6e04e284f9f999280e0824cddce73db3c30af8cd9a3558d48def341eb05bb5b2.png","timeStamp":1607545739153}],"result":"SUCCESS","precondition":false,"level":1},{"number":15,"description":"Criar Tarefa: Clicar Selecionar Perfil","duration":390,"startTime":"2020-12-09T17:28:59.153-03:00[America/Sao_Paulo]","screenshots":[{"screenshot":"6e04e284f9f999280e0824cddce73db3c30af8cd9a3558d48def341eb05bb5b2.png","timeStamp":1607545739543}],"result":"SUCCESS","precondition":false,"level":1},{"number":16,"description":"Criar Tarefa: Preencher Plataforma","duration":481,"startTime":"2020-12-09T17:28:59.544-03:00[America/Sao_Paulo]","screenshots":[{"screenshot":"b82d33728750eb99221936f281642d4df717fb3fd3d7e1141195ef0a1242c0ec.png","timeStamp":1607545740025}],"result":"SUCCESS","precondition":false,"level":1},{"number":17,"description":"Criar Tarefa: Preencher SO","duration":498,"startTime":"2020-12-09T17:29:00.026-03:00[America/Sao_Paulo]","screenshots":[{"screenshot":"f209cf90699f52e9e5bc4e8f0df5d08db7ee30210ea514f3455d621ea6bb451a.png","timeStamp":1607545740523}],"result":"SUCCESS","precondition":false,"level":1},{"number":18,"description":"Criar Tarefa: Preencher Versao SO","duration":470,"startTime":"2020-12-09T17:29:00.524-03:00[America/Sao_Paulo]","screenshots":[{"screenshot":"2f54d5506fdf7d80f6df6cb27ea03874568644a934a0b515b0759a3b30092bf9.png","timeStamp":1607545740994}],"result":"SUCCESS","precondition":false,"level":1},{"number":19,"description":"Criar Tarefa: Selecionar Categoria Atribuir","duration":453,"startTime":"2020-12-09T17:29:00.994-03:00[America/Sao_Paulo]","screenshots":[{"screenshot":"b01e79c7eb07defd3d4b11adb218231e3e6da5735d75f6b0e27bd4565b01704b.png","timeStamp":1607545741447}],"result":"SUCCESS","precondition":false,"level":1},{"number":20,"description":"Criar Tarefa: Preencher Resumo","duration":486,"startTime":"2020-12-09T17:29:01.448-03:00[America/Sao_Paulo]","screenshots":[{"screenshot":"09466835f0d9d01fca3bf423554393201e56bd33bc32aac8cc73e123c47aa19a.png","timeStamp":1607545741934}],"result":"SUCCESS","precondition":false,"level":1},{"number":21,"description":"Criar Tarefa: Preencher Descricao","duration":472,"startTime":"2020-12-09T17:29:01.935-03:00[America/Sao_Paulo]","screenshots":[{"screenshot":"0b085076c0ae8d549674fd0d04f119bafb7469ffb7d5b35950a2f45bf6db994a.png","timeStamp":1607545742407}],"result":"SUCCESS","precondition":false,"level":1},{"number":22,"description":"Criar Tarefa: Preencher Passos Para Reproduzir","duration":434,"startTime":"2020-12-09T17:29:02.408-03:00[America/Sao_Paulo]","screenshots":[{"screenshot":"7015f95c48a401f87acc3f341b408d51b438b9b48424966ee644f20fd20497af.png","timeStamp":1607545742842}],"result":"SUCCESS","precondition":false,"level":1},{"number":23,"description":"Criar Tarefa: Preencher Informacoes Adicionais","duration":463,"startTime":"2020-12-09T17:29:02.842-03:00[America/Sao_Paulo]","screenshots":[{"screenshot":"e82544a273f7190b7f2c9e15e5e8492fe5632fea72c130a06a9eca8fcac9f074.png","timeStamp":1607545743305}],"result":"SUCCESS","precondition":false,"level":1},{"number":24,"description":"Criar Tarefa: Clicar Visibilidade Publico","duration":436,"startTime":"2020-12-09T17:29:03.306-03:00[America/Sao_Paulo]","screenshots":[{"screenshot":"a4f11f05fbd8e4151f42430a2efdf6e34eecf611be7122e1ae736add4b1f1412.png","timeStamp":1607545743742}],"result":"SUCCESS","precondition":false,"level":1},{"number":25,"description":"Criar Tarefa: Clicar Criar Nova Tarefa","duration":571,"startTime":"2020-12-09T17:29:03.743-03:00[America/Sao_Paulo]","screenshots":[{"screenshot":"be5ba05b7a0318324485c3bb94bb442bc5ffab57436aee18cd07a95675905a87.png","timeStamp":1607545744314}],"result":"SUCCESS","precondition":false,"level":1}]},{"number":26,"description":"Then Sistema retorna mensagem de tarefa criada com \u0027Operação realizada com sucesso.\u0027","duration":2200,"startTime":"2020-12-09T17:29:04.315-03:00[America/Sao_Paulo]","screenshots":[{"screenshot":"bca2d7c146011bf3fa296fb38e8ded1f195adf10cac49684d83ad14036100b3d.png","timeStamp":1607545746515}],"result":"SUCCESS","precondition":false,"level":0,"children":[{"number":27,"description":"Criar Tarefa: retorna MSG Ao Salvar Tarefa","duration":410,"startTime":"2020-12-09T17:29:04.316-03:00[America/Sao_Paulo]","screenshots":[{"screenshot":"be5ba05b7a0318324485c3bb94bb442bc5ffab57436aee18cd07a95675905a87.png","timeStamp":1607545744726}],"result":"SUCCESS","precondition":false,"level":1},{"number":28,"description":"Ver tarefas: retornar ID Da Tarefa TextArea","duration":1787,"startTime":"2020-12-09T17:29:04.727-03:00[America/Sao_Paulo]","screenshots":[{"screenshot":"bca2d7c146011bf3fa296fb38e8ded1f195adf10cac49684d83ad14036100b3d.png","timeStamp":1607545746514}],"result":"SUCCESS","precondition":false,"level":1}]},{"number":29,"description":"When clico em \u0027Criar Tarefa\u0027","duration":568,"startTime":"2020-12-09T17:29:06.515-03:00[America/Sao_Paulo]","screenshots":[{"screenshot":"dcdb627d28828bf20d7799ef8d1191d93f21c2df7efee5e3a74fe29d01bca8e7.png","timeStamp":1607545747083}],"result":"SUCCESS","precondition":false,"level":0,"children":[{"number":30,"description":"main: Clicar Em Criar Tarefa","duration":565,"startTime":"2020-12-09T17:29:06.516-03:00[America/Sao_Paulo]","screenshots":[{"screenshot":"dcdb627d28828bf20d7799ef8d1191d93f21c2df7efee5e3a74fe29d01bca8e7.png","timeStamp":1607545747081}],"result":"SUCCESS","precondition":false,"level":1}]},{"number":31,"description":"And preencho os detalhes do relatorio\r\n| Categoria | Frequencia | Gravidade | Prioridade | Selecionar Perfil | Plataforma | SO | Versao SO | Atribuir | Resumo | Descricao | Passos Reproduzir | informacoes Adicionais | Aplicar Marcadores | Anexo | Visibilidade |\r\n| categ inicial | sempre | pequeno | normal | Sim | plat teste | win | 10 | administrator | Tarefa de teste para apagar | Descricao de tarefa de teste automatizado | clicar e preencher | outro teste | . | Nao | publico |","duration":6864,"startTime":"2020-12-09T17:29:07.083-03:00[America/Sao_Paulo]","screenshots":[{"screenshot":"7667e593ba94e1ceece0b78a320fc873687f8ba5697780525ff9862f67a8e7f9.png","timeStamp":1607545753947}],"result":"SUCCESS","precondition":false,"level":0,"children":[{"number":32,"description":"Criar Tarefa: Selecionar Categoria","duration":493,"startTime":"2020-12-09T17:29:07.084-03:00[America/Sao_Paulo]","screenshots":[{"screenshot":"680267e4e6f27f73213475bf815bdb827a416d37f1e35f690b4ac1d0afb81d13.png","timeStamp":1607545747577}],"result":"SUCCESS","precondition":false,"level":1},{"number":33,"description":"Criar Tarefa: Selecionar Frequencia","duration":459,"startTime":"2020-12-09T17:29:07.577-03:00[America/Sao_Paulo]","screenshots":[{"screenshot":"96e2db8cc0448a4ccd716a9435c58e25ce30927c3bb6913e2e0ec97b6aa82aa6.png","timeStamp":1607545748036}],"result":"SUCCESS","precondition":false,"level":1},{"number":34,"description":"Criar Tarefa: Selecionar Gravidade","duration":417,"startTime":"2020-12-09T17:29:08.037-03:00[America/Sao_Paulo]","screenshots":[{"screenshot":"96e2db8cc0448a4ccd716a9435c58e25ce30927c3bb6913e2e0ec97b6aa82aa6.png","timeStamp":1607545748454}],"result":"SUCCESS","precondition":false,"level":1},{"number":35,"description":"Criar Tarefa: Selecionar Prioridade","duration":419,"startTime":"2020-12-09T17:29:08.454-03:00[America/Sao_Paulo]","screenshots":[{"screenshot":"96e2db8cc0448a4ccd716a9435c58e25ce30927c3bb6913e2e0ec97b6aa82aa6.png","timeStamp":1607545748873}],"result":"SUCCESS","precondition":false,"level":1},{"number":36,"description":"Criar Tarefa: Clicar Selecionar Perfil","duration":373,"startTime":"2020-12-09T17:29:08.873-03:00[America/Sao_Paulo]","screenshots":[{"screenshot":"96e2db8cc0448a4ccd716a9435c58e25ce30927c3bb6913e2e0ec97b6aa82aa6.png","timeStamp":1607545749246}],"result":"SUCCESS","precondition":false,"level":1},{"number":37,"description":"Criar Tarefa: Preencher Plataforma","duration":486,"startTime":"2020-12-09T17:29:09.246-03:00[America/Sao_Paulo]","screenshots":[{"screenshot":"11b849f42f79d03abdfd5788619b7294a7cd2489e62f7c419d7c3119ba59f00f.png","timeStamp":1607545749732}],"result":"SUCCESS","precondition":false,"level":1},{"number":38,"description":"Criar Tarefa: Preencher SO","duration":469,"startTime":"2020-12-09T17:29:09.733-03:00[America/Sao_Paulo]","screenshots":[{"screenshot":"73c62abd6882fa43b0eff67a865f519070e80a85048f1d63b6568a7fa91ca321.png","timeStamp":1607545750202}],"result":"SUCCESS","precondition":false,"level":1},{"number":39,"description":"Criar Tarefa: Preencher Versao SO","duration":430,"startTime":"2020-12-09T17:29:10.203-03:00[America/Sao_Paulo]","screenshots":[{"screenshot":"a812a6572f1601c6c08d21864853a5316b0916ddb927ca50be6ba14418805235.png","timeStamp":1607545750633}],"result":"SUCCESS","precondition":false,"level":1},{"number":40,"description":"Criar Tarefa: Selecionar Categoria Atribuir","duration":459,"startTime":"2020-12-09T17:29:10.633-03:00[America/Sao_Paulo]","screenshots":[{"screenshot":"b6d804285340fe7c0d909c25f92a4867841a397f45378a5ab16bb0c9c062b73a.png","timeStamp":1607545751092}],"result":"SUCCESS","precondition":false,"level":1},{"number":41,"description":"Criar Tarefa: Preencher Resumo","duration":465,"startTime":"2020-12-09T17:29:11.093-03:00[America/Sao_Paulo]","screenshots":[{"screenshot":"ea8271185ecfdb7c3f12e44fc5ef394d38d302ee2ab078a3b189aee653832ecc.png","timeStamp":1607545751558}],"result":"SUCCESS","precondition":false,"level":1},{"number":42,"description":"Criar Tarefa: Preencher Descricao","duration":483,"startTime":"2020-12-09T17:29:11.558-03:00[America/Sao_Paulo]","screenshots":[{"screenshot":"a15b7e29e58318b720de0186991ad010804a2ec7299033fdc4c1bffc79f00192.png","timeStamp":1607545752041}],"result":"SUCCESS","precondition":false,"level":1},{"number":43,"description":"Criar Tarefa: Preencher Passos Para Reproduzir","duration":436,"startTime":"2020-12-09T17:29:12.041-03:00[America/Sao_Paulo]","screenshots":[{"screenshot":"e1afc8ff9f48493d2b7d517139f056098869d6f77b685f682aa80cab81601642.png","timeStamp":1607545752477}],"result":"SUCCESS","precondition":false,"level":1},{"number":44,"description":"Criar Tarefa: Preencher Informacoes Adicionais","duration":438,"startTime":"2020-12-09T17:29:12.478-03:00[America/Sao_Paulo]","screenshots":[{"screenshot":"e82544a273f7190b7f2c9e15e5e8492fe5632fea72c130a06a9eca8fcac9f074.png","timeStamp":1607545752916}],"result":"SUCCESS","precondition":false,"level":1},{"number":45,"description":"Criar Tarefa: Clicar Visibilidade Publico","duration":429,"startTime":"2020-12-09T17:29:12.916-03:00[America/Sao_Paulo]","screenshots":[{"screenshot":"a4f11f05fbd8e4151f42430a2efdf6e34eecf611be7122e1ae736add4b1f1412.png","timeStamp":1607545753345}],"result":"SUCCESS","precondition":false,"level":1},{"number":46,"description":"Criar Tarefa: Clicar Criar Nova Tarefa","duration":599,"startTime":"2020-12-09T17:29:13.346-03:00[America/Sao_Paulo]","screenshots":[{"screenshot":"7667e593ba94e1ceece0b78a320fc873687f8ba5697780525ff9862f67a8e7f9.png","timeStamp":1607545753945}],"result":"SUCCESS","precondition":false,"level":1}]},{"number":47,"description":"And defino relação de \u0027é filho de\u0027 para outra tarefa","duration":3471,"startTime":"2020-12-09T17:29:13.947-03:00[America/Sao_Paulo]","screenshots":[{"screenshot":"dfdd9c2027304d773fa37bbd098dddebfdf31449d9bf855a49e2dffb64829f37.png","timeStamp":1607545757418}],"result":"SUCCESS","precondition":false,"level":0,"children":[{"number":48,"description":"Ver tarefas: definir Relacao Da Tarefa","duration":2286,"startTime":"2020-12-09T17:29:13.948-03:00[America/Sao_Paulo]","screenshots":[{"screenshot":"ee4a107e2f1b0837f7e5e53909586f9f5307b992b927b5f9da9ef330780d7746.png","timeStamp":1607545756234}],"result":"SUCCESS","precondition":false,"level":1},{"number":49,"description":"Ver tarefas: definir Tarefa Da Relacao","duration":442,"startTime":"2020-12-09T17:29:16.235-03:00[America/Sao_Paulo]","screenshots":[{"screenshot":"4e64fb720c5652cc598c6205f2076260afa519c78c5cf51984a76b251db5bb36.png","timeStamp":1607545756677}],"result":"SUCCESS","precondition":false,"level":1},{"number":50,"description":"Ver tarefas: adicionar Relacionamento De Tarefas","duration":739,"startTime":"2020-12-09T17:29:16.678-03:00[America/Sao_Paulo]","screenshots":[{"screenshot":"dfdd9c2027304d773fa37bbd098dddebfdf31449d9bf855a49e2dffb64829f37.png","timeStamp":1607545757417}],"result":"SUCCESS","precondition":false,"level":1}]},{"number":51,"description":"Then A situação da tarefa se encontra \u0027true\u0027 na tela de ver tarefas","duration":25,"startTime":"2020-12-09T17:29:17.418-03:00[America/Sao_Paulo]","screenshots":[{"screenshot":"dfdd9c2027304d773fa37bbd098dddebfdf31449d9bf855a49e2dffb64829f37.png","timeStamp":1607545757443}],"result":"SUCCESS","precondition":false,"level":0,"children":[{"number":52,"description":"Ver tarefas: verifico Tarefa Criado","duration":23,"startTime":"2020-12-09T17:29:17.419-03:00[America/Sao_Paulo]","screenshots":[{"screenshot":"dfdd9c2027304d773fa37bbd098dddebfdf31449d9bf855a49e2dffb64829f37.png","timeStamp":1607545757442}],"result":"SUCCESS","precondition":false,"level":1}]}],"userStory":{"id":"criar-nova-tarefa","storyName":"Criar nova tarefa","path":"src/test/resources/features/criarTarefa.feature","type":"feature"},"featureTag":{"name":"Features/Criar nova tarefa","type":"feature","displayName":"Features/Criar nova tarefa"},"title":"adicionar relacionamento entre tarefas","tags":[{"name":"Criar nova tarefa","type":"feature","displayName":"Criar nova tarefa"}],"startTime":"2020-12-09T17:28:47.179-03:00[America/Sao_Paulo]","duration":30264,"projectKey":"","sessionId":"650b38f1fc252e6473d403452abe61db","driver":"chrome","isManualTestingUpToDate":false,"manual":false,"testSource":"Cucumber","result":"SUCCESS"}