{"name":"adiciono um novo subprojeto","id":"criar-novo-projeto;adiciono-um-novo-subprojeto","testSteps":[{"number":1,"description":"Abrir Mantis","duration":695,"startTime":"2020-12-09T17:35:11.480-03:00[America/Sao_Paulo]","screenshots":[{"screenshot":"20751074aa616d8ca32771653149891b111e8474db230b8c59b587eca783e230.png","timeStamp":1607546112175}],"result":"SUCCESS","precondition":false,"level":0},{"number":2,"description":"Preencher usuário com \u0027administrator\u0027","duration":409,"startTime":"2020-12-09T17:35:12.175-03:00[America/Sao_Paulo]","screenshots":[{"screenshot":"f253a7bf9b1dbe68897d229ece9f30eed6040e767175ee6ad7d5b4a098b02cef.png","timeStamp":1607546112584}],"result":"SUCCESS","precondition":false,"level":0},{"number":3,"description":"Clicar em \u0027Login\u0027","duration":658,"startTime":"2020-12-09T17:35:12.585-03:00[America/Sao_Paulo]","screenshots":[{"screenshot":"3a2498f18daea4991195fc522036a7a7fcf99153bb5493a9ebb867ee499a26ca.png","timeStamp":1607546113243}],"result":"SUCCESS","precondition":false,"level":0},{"number":4,"description":"Preencher senha com \u0027[0}\u0027","duration":400,"startTime":"2020-12-09T17:35:13.244-03:00[America/Sao_Paulo]","screenshots":[{"screenshot":"6653342e027a26d83a6bdb40034c4a3699f9e894bcd1ef855f4cbc5175ef1fb6.png","timeStamp":1607546113644}],"result":"SUCCESS","precondition":false,"level":0},{"number":5,"description":"Clicar em \u0027Login\u0027","duration":965,"startTime":"2020-12-09T17:35:13.645-03:00[America/Sao_Paulo]","screenshots":[{"screenshot":"e774c20a8b7032c56cde559c5dcd03995d894e6b4f287c7d54e833f994a79852.png","timeStamp":1607546114610}],"result":"SUCCESS","precondition":false,"level":0},{"number":6,"description":"Given que estou logado como administrador no sistema","duration":475,"startTime":"2020-12-09T17:35:14.611-03:00[America/Sao_Paulo]","screenshots":[{"screenshot":"e774c20a8b7032c56cde559c5dcd03995d894e6b4f287c7d54e833f994a79852.png","timeStamp":1607546115086}],"result":"SUCCESS","precondition":false,"level":0,"children":[{"number":7,"description":"Retorna username das informações de login","duration":417,"startTime":"2020-12-09T17:35:14.668-03:00[America/Sao_Paulo]","screenshots":[{"screenshot":"e774c20a8b7032c56cde559c5dcd03995d894e6b4f287c7d54e833f994a79852.png","timeStamp":1607546115085}],"result":"SUCCESS","precondition":false,"level":1}]},{"number":8,"description":"When clico em \u0027gerenciar\u0027","duration":675,"startTime":"2020-12-09T17:35:15.086-03:00[America/Sao_Paulo]","screenshots":[{"screenshot":"25ee4b24bfd6663806f96b9957d7d85183028e12808080492e2b17cd57c183c2.png","timeStamp":1607546115761}],"result":"SUCCESS","precondition":false,"level":0,"children":[{"number":9,"description":"main: Clicar Em Gerenciar","duration":592,"startTime":"2020-12-09T17:35:15.168-03:00[America/Sao_Paulo]","screenshots":[{"screenshot":"25ee4b24bfd6663806f96b9957d7d85183028e12808080492e2b17cd57c183c2.png","timeStamp":1607546115760}],"result":"SUCCESS","precondition":false,"level":1}]},{"number":10,"description":"And clico em gerenciar \u0027projetos\u0027","duration":634,"startTime":"2020-12-09T17:35:15.761-03:00[America/Sao_Paulo]","screenshots":[{"screenshot":"ac187d528d49d492a38b6ca35002c684fce4ce1a3fea062c69c018712bdb0db8.png","timeStamp":1607546116395}],"result":"SUCCESS","precondition":false,"level":0,"children":[{"number":11,"description":"Gerenciar Page: clicar Gerenciar Projetos","duration":632,"startTime":"2020-12-09T17:35:15.762-03:00[America/Sao_Paulo]","screenshots":[{"screenshot":"ac187d528d49d492a38b6ca35002c684fce4ce1a3fea062c69c018712bdb0db8.png","timeStamp":1607546116394}],"result":"SUCCESS","precondition":false,"level":1}]},{"number":12,"description":"And Verifico a necessidade de excluir projeto \u0027projetoto master\u0027","duration":2499,"startTime":"2020-12-09T17:35:16.395-03:00[America/Sao_Paulo]","screenshots":[{"screenshot":"ac187d528d49d492a38b6ca35002c684fce4ce1a3fea062c69c018712bdb0db8.png","timeStamp":1607546118894}],"result":"SUCCESS","precondition":false,"level":0,"children":[{"number":13,"description":"Criar Projeto: verifico Projeto Criado","duration":2406,"startTime":"2020-12-09T17:35:16.487-03:00[America/Sao_Paulo]","screenshots":[{"screenshot":"ac187d528d49d492a38b6ca35002c684fce4ce1a3fea062c69c018712bdb0db8.png","timeStamp":1607546118893}],"result":"SUCCESS","precondition":false,"level":1}]},{"number":14,"description":"And clico em criar novo projeto","duration":543,"startTime":"2020-12-09T17:35:18.894-03:00[America/Sao_Paulo]","screenshots":[{"screenshot":"f8e3b0c6e40f0c9b6bdce9679ae840893ffb12aa4a28ae10974a35cf2fb4ac7b.png","timeStamp":1607546119437}],"result":"SUCCESS","precondition":false,"level":0,"children":[{"number":15,"description":"Gerenciar Projetos Page: clicar Criar Novo Projeto","duration":541,"startTime":"2020-12-09T17:35:18.895-03:00[America/Sao_Paulo]","screenshots":[{"screenshot":"f8e3b0c6e40f0c9b6bdce9679ae840893ffb12aa4a28ae10974a35cf2fb4ac7b.png","timeStamp":1607546119436}],"result":"SUCCESS","precondition":false,"level":1}]},{"number":16,"description":"And preencho os detalhes do projeto:\r\n| Nome Projeto | Estado | Herdar Globais | Visibilidade | Descricao |\r\n| Aleatorio | desenvolvimento | Sim | público | Projeto preenchido pelo teste de automação |","duration":2354,"startTime":"2020-12-09T17:35:19.437-03:00[America/Sao_Paulo]","screenshots":[{"screenshot":"fa096f2fb764ad11bc38c25ba27d9ba57358a3aeb64dbad923dd9037bdc4531c.png","timeStamp":1607546121791}],"result":"SUCCESS","precondition":false,"level":0,"children":[{"number":17,"description":"Criar Projeto: preencher Nome Projeto","duration":470,"startTime":"2020-12-09T17:35:19.438-03:00[America/Sao_Paulo]","screenshots":[{"screenshot":"ed75b7d28d52fd37c0671605e7474c1d52a6c0716db5bd18e9a4c34bcbd3777c.png","timeStamp":1607546119908}],"result":"SUCCESS","precondition":false,"level":1},{"number":18,"description":"Criar Projeto: selecionar Estado","duration":426,"startTime":"2020-12-09T17:35:19.909-03:00[America/Sao_Paulo]","screenshots":[{"screenshot":"af92a636bb1b84d77cf25d82f1b163e5881490da7d710da62af6968954828a19.png","timeStamp":1607546120335}],"result":"SUCCESS","precondition":false,"level":1},{"number":19,"description":"Criar Projeto: selecionar Visibilidade","duration":425,"startTime":"2020-12-09T17:35:20.335-03:00[America/Sao_Paulo]","screenshots":[{"screenshot":"ed75b7d28d52fd37c0671605e7474c1d52a6c0716db5bd18e9a4c34bcbd3777c.png","timeStamp":1607546120760}],"result":"SUCCESS","precondition":false,"level":1},{"number":20,"description":"Criar Projeto: preencher Descricao","duration":486,"startTime":"2020-12-09T17:35:20.761-03:00[America/Sao_Paulo]","screenshots":[{"screenshot":"0d19fab34bb6d4d20ef1801e8a43efe71bc909410f3e3aa9d947f501163f4857.png","timeStamp":1607546121247}],"result":"SUCCESS","precondition":false,"level":1},{"number":21,"description":"Criar Projeto: clicar Adicionar Projeto","duration":542,"startTime":"2020-12-09T17:35:21.247-03:00[America/Sao_Paulo]","screenshots":[{"screenshot":"fa096f2fb764ad11bc38c25ba27d9ba57358a3aeb64dbad923dd9037bdc4531c.png","timeStamp":1607546121789}],"result":"SUCCESS","precondition":false,"level":1}]},{"number":22,"description":"And acesso o projeto criado","duration":4513,"startTime":"2020-12-09T17:35:21.792-03:00[America/Sao_Paulo]","screenshots":[{"screenshot":"1bb31f8e7d542b6f2fe21b2dd9aa0fad498fc2e5370b92b1c699b67975e174a4.png","timeStamp":1607546126305}],"result":"SUCCESS","precondition":false,"level":0,"children":[{"number":23,"description":"Criar Projeto: acesso Projeto Criado","duration":4512,"startTime":"2020-12-09T17:35:21.792-03:00[America/Sao_Paulo]","screenshots":[{"screenshot":"1bb31f8e7d542b6f2fe21b2dd9aa0fad498fc2e5370b92b1c699b67975e174a4.png","timeStamp":1607546126304}],"result":"SUCCESS","precondition":false,"level":1}]},{"number":24,"description":"And adiciono subprojeto ja existente","duration":1025,"startTime":"2020-12-09T17:35:26.305-03:00[America/Sao_Paulo]","screenshots":[{"screenshot":"e187bbd063a1ba6b63386e988100e69528436d61f884f9d980c7afdf46648131.png","timeStamp":1607546127330}],"result":"SUCCESS","precondition":false,"level":0,"children":[{"number":25,"description":"Gerenciar Projetos: selecionar SubProjeto","duration":450,"startTime":"2020-12-09T17:35:26.306-03:00[America/Sao_Paulo]","screenshots":[{"screenshot":"55cc62c82ea908273e58b0e22af4e8761297a23d0a77ad03ebf38e3879448331.png","timeStamp":1607546126756}],"result":"SUCCESS","precondition":false,"level":1},{"number":26,"description":"Gerenciar Projetos: clicar Em Adicionar Como Subprojeto","duration":573,"startTime":"2020-12-09T17:35:26.756-03:00[America/Sao_Paulo]","screenshots":[{"screenshot":"e187bbd063a1ba6b63386e988100e69528436d61f884f9d980c7afdf46648131.png","timeStamp":1607546127329}],"result":"SUCCESS","precondition":false,"level":1}]},{"number":27,"description":"Then Sistema retorna mensagem de projeto criado com \u0027Operação realizada com sucesso.\u0027","duration":374,"startTime":"2020-12-09T17:35:27.331-03:00[America/Sao_Paulo]","screenshots":[{"screenshot":"e187bbd063a1ba6b63386e988100e69528436d61f884f9d980c7afdf46648131.png","timeStamp":1607546127705}],"result":"SUCCESS","precondition":false,"level":0,"children":[{"number":28,"description":"Criar Projeto: retorna MSG Ao Salvar Projeto","duration":373,"startTime":"2020-12-09T17:35:27.331-03:00[America/Sao_Paulo]","screenshots":[{"screenshot":"e187bbd063a1ba6b63386e988100e69528436d61f884f9d980c7afdf46648131.png","timeStamp":1607546127704}],"result":"SUCCESS","precondition":false,"level":1}]}],"userStory":{"id":"criar-novo-projeto","storyName":"Criar novo projeto","path":"src/test/resources/features/gerenciarProjetos.feature","type":"feature"},"featureTag":{"name":"Features/Criar novo projeto","type":"feature","displayName":"Features/Criar novo projeto"},"title":"adiciono um novo subprojeto","tags":[{"name":"SbuProjeto","type":"tag","displayName":"SbuProjeto"},{"name":"Criar novo projeto","type":"feature","displayName":"Criar novo projeto"}],"startTime":"2020-12-09T17:35:05.791-03:00[America/Sao_Paulo]","duration":21915,"projectKey":"","sessionId":"9d9f8a70b4bc1a880e2bd94b53380b02","driver":"chrome","isManualTestingUpToDate":false,"manual":false,"testSource":"Cucumber","result":"SUCCESS"}